shoutbox/__init__.py
shoutbox/client.py
shoutbox/exceptions.py
shoutbox/models.py
shoutbox/smtp.py
shoutboxnet-0.1.7.dist-info/licenses/LICENSE
shoutboxnet-0.1.7.dist-info/METADATA
shoutboxnet-0.1.7.dist-info/WHEEL
shoutboxnet-0.1.7.dist-info/top_level.txt
shoutboxnet-0.1.7.dist-info/RECORD
