Metadata-Version: 2.4
Name: shoutboxnet
Version: 0.1.7
Summary: A Python client for the Shoutbox Email API
Home-page: https://github.com/shoutboxnet/python
Author: Tycho Luyben
Author-email: Tycho Luyben <tycho@shoutbox.net>
License: MIT
Project-URL: Homepage, https://shoutbox.net
Project-URL: Documentation, https://shoutbox.net/docs
Project-URL: Repository, https://github.com/shoutboxnet/python.git
Project-URL: Bug Tracker, https://github.com/shoutboxnet/python/issues
Keywords: email,api,client
Classifier: Development Status :: 4 - Beta
Classifier: Intended Audience :: Developers
Classifier: License :: OSI Approved :: MIT License
Classifier: Programming Language :: Python :: 3
Classifier: Programming Language :: Python :: 3.7
Classifier: Programming Language :: Python :: 3.8
Classifier: Programming Language :: Python :: 3.9
Classifier: Programming Language :: Python :: 3.10
Classifier: Programming Language :: Python :: 3.11
Requires-Python: >=3.7
License-File: LICENSE
Requires-Dist: requests>=2.25.0
Provides-Extra: dev
Requires-Dist: pytest>=6.0; extra == "dev"
Requires-Dist: pytest-cov>=2.0; extra == "dev"
Requires-Dist: black>=22.0; extra == "dev"
Requires-Dist: isort>=5.0; extra == "dev"
Requires-Dist: flake8>=3.9; extra == "dev"
Requires-Dist: mypy>=0.900; extra == "dev"
Requires-Dist: sphinx>=4.0; extra == "dev"
Requires-Dist: sphinx-rtd-theme>=1.0; extra == "dev"
Dynamic: license-file
